[
  {
    "酒样名称": "泸州1#",
    "酒度": 52,
    "总分": 94.6,
    "设备": "泥窖",
    "发酵剂": "大曲"
  },
  {
    "酒样名称": "泸州2#",
    "酒度": 52,
    "总分": 93.6,
    "设备": "泥窖",
    "发酵剂": "大曲"
  },
  {
    "酒样名称": "泸州3#",
    "酒度": 52,
    "总分": 92.6,
    "设备": "泥窖",
    "发酵剂": "大曲"
  },
  {
    "酒样名称": "泸州4#",
    "酒度": 52,
    "总分": 90.2,
    "设备": "泥窖",
    "发酵剂": "大曲"
  },
  {
    "酒样名称": "泸州5#",
    "酒度": 52,
    "总分": 88.8,
    "设备": "泥窖",
    "发酵剂": "大曲"
  },
  {
    "酒样名称": "洋河1#",
    "酒度": 55,
    "总分": 94.0,
    "设备": "泥窖",
    "发酵剂": "大曲"
  },
  {
    "酒样名称": "洋河2#",
    "酒度": 55,
    "总分": 93.0,
    "设备": "泥窖",
    "发酵剂": "大曲"
  },
  {
    "酒样名称": "洋河3#",
    "酒度": 55,
    "总分": 91.8,
    "设备": "泥窖",
    "发酵剂": "大曲"
  },
  {
    "酒样名称": "洋河4#",
    "酒度": 55,
    "总分": 89.6,
    "设备": "泥窖",
    "发酵剂": "大曲"
  },
  {
    "酒样名称": "洋河5#",
    "酒度": 55,
    "总分": 88.0,
    "设备": "泥窖",
    "发酵剂": "大曲"
  },
  {
    "酒样名称": "五粮液1#",
    "酒度": 52,
    "总分": 94.6,
    "设备": "泥窖",
    "发酵剂": "大曲"
  },
  {
    "酒样名称": "五粮液2#",
    "酒度": 52,
    "总分": 93.6,
    "设备": "泥窖",
    "发酵剂": "大曲"
  },
  {
    "酒样名称": "五粮液3#",
    "酒度": 52,
    "总分": 92.2,
    "设备": "泥窖",
    "发酵剂": "大曲"
  },
  {
    "酒样名称": "五粮液4#",
    "酒度": 52,
    "总分": 90.4,
    "设备": "泥窖",
    "发酵剂": "大曲"
  },
  {
    "酒样名称": "五粮液5#",
    "酒度": 52,
    "总分": 88.4,
    "设备": "泥窖",
    "发酵剂": "大曲"
  },
  {
    "酒样名称": "汾酒1#",
    "酒度": 53,
    "总分": 94.2,
    "设备": "地缸",
    "发酵剂": "大曲"
  },
  {
    "酒样名称": "汾酒2#",
    "酒度": 53,
    "总分": 93.6,
    "设备": "地缸",
    "发酵剂": "大曲"
  },
  {
    "酒样名称": "汾酒3#",
    "酒度": 53,
    "总分": 92.4,
    "设备": "地缸",
    "发酵剂": "大曲"
  },
  {
    "酒样名称": "汾酒4#",
    "酒度": 53,
    "总分": 90.6,
    "设备": "地缸",
    "发酵剂": "大曲"
  },
  {
    "酒样名称": "汾酒5#",
    "酒度": 53,
    "总分": 88.8,
    "设备": "地缸",
    "发酵剂": "大曲"
  },
  {
    "酒样名称": "江津1#",
    "酒度": 50,
    "总分": 93.0,
    "设备": "石窖",
    "发酵剂": "小曲"
  },
  {
    "酒样名称": "江津2#",
    "酒度": 50,
    "总分": 91.0,
    "设备": "石窖",
    "发酵剂": "小曲"
  },
  {
    "酒样名称": "江津3#",
    "酒度": 50,
    "总分": 89.0,
    "设备": "石窖",
    "发酵剂": "小曲"
  },
  {
    "酒样名称": "江津4#",
    "酒度": 50,
    "总分": 88.0,
    "设备": "石窖",
    "发酵剂": "小曲"
  },
  {
    "酒样名称": "江津5#",
    "酒度": 50,
    "总分": 87.0,
    "设备": "石窖",
    "发酵剂": "小曲"
  },
  {
    "酒样名称": "郎酒1#",
    "酒度": 53,
    "总分": 94.2,
    "设备": "石窖",
    "发酵剂": "大曲"
  },
  {
    "酒样名称": "郎酒2#",
    "酒度": 53,
    "总分": 93.4,
    "设备": "石窖",
    "发酵剂": "大曲"
  },
  {
    "酒样名称": "郎酒3#",
    "酒度": 53,
    "总分": 91.4,
    "设备": "石窖",
    "发酵剂": "大曲"
  },
  {
    "酒样名称": "郎酒4#",
    "酒度": 53,
    "总分": 91.0,
    "设备": "石窖",
    "发酵剂": "大曲"
  },
  {
    "酒样名称": "郎酒5#",
    "酒度": 53,
    "总分": 89.6,
    "设备": "石窖",
    "发酵剂": "大曲"
  },
  {
    "酒样名称": "习酒1#",
    "酒度": 53,
    "总分": 93.8,
    "设备": "石窖",
    "发酵剂": "大曲"
  },
  {
    "酒样名称": "习酒2#",
    "酒度": 53,
    "总分": 93.4,
    "设备": "石窖",
    "发酵剂": "大曲"
  },
  {
    "酒样名称": "习酒3#",
    "酒度": 53,
    "总分": 92.0,
    "设备": "石窖",
    "发酵剂": "大曲"
  },
  {
    "酒样名称": "习酒4#",
    "酒度": 53,
    "总分": 91.0,
    "设备": "石窖",
    "发酵剂": "大曲"
  },
  {
    "酒样名称": "习酒5#",
    "酒度": 53,
    "总分": 88.2,
    "设备": "石窖",
    "发酵剂": "大曲"
  },
  {
    "酒样名称": "茅台1#",
    "酒度": 53,
    "总分": 94.8,
    "设备": "石窖",
    "发酵剂": "大曲"
  },
  {
    "酒样名称": "茅台2#",
    "酒度": 53,
    "总分": 93.8,
    "设备": "石窖",
    "发酵剂": "大曲"
  },
  {
    "酒样名称": "茅台3#",
    "酒度": 53,
    "总分": 93.0,
    "设备": "石窖",
    "发酵剂": "大曲"
  },
  {
    "酒样名称": "茅台4#",
    "酒度": 53,
    "总分": 91.4,
    "设备": "石窖",
    "发酵剂": "大曲"
  },
  {
    "酒样名称": "茅台5#",
    "酒度": 53,
    "总分": 89.2,
    "设备": "石窖",
    "发酵剂": "大曲"
  },
  {
    "酒样名称": "天龙泉1#",
    "酒度": 55,
    "总分": 93.0,
    "设备": "陶罐,发酵罐",
    "发酵剂": "小曲"
  },
  {
    "酒样名称": "天龙泉2#",
    "酒度": 52,
    "总分": 92.4,
    "设备": "陶罐,发酵罐",
    "发酵剂": "小曲"
  },
  {
    "酒样名称": "天龙泉3#",
    "酒度": 52,
    "总分": 91.6,
    "设备": "陶罐,发酵罐",
    "发酵剂": "小曲"
  },
  {
    "酒样名称": "天龙泉4#",
    "酒度": 52,
    "总分": 89.4,
    "设备": "陶罐,发酵罐",
    "发酵剂": "小曲"
  },
  {
    "酒样名称": "天龙泉5#",
    "酒度": 52,
    "总分": 87.6,
    "设备": "陶罐,发酵罐",
    "发酵剂": "小曲"
  },
  {
    "酒样名称": "白云边1#",
    "酒度": 45,
    "总分": 94.0,
    "设备": "砖窖",
    "发酵剂": "大曲"
  },
  {
    "酒样名称": "白云边2#",
    "酒度": 45,
    "总分": 93.2,
    "设备": "砖窖",
    "发酵剂": "大曲"
  },
  {
    "酒样名称": "白云边3#",
    "酒度": 45,
    "总分": 92.0,
    "设备": "砖窖",
    "发酵剂": "大曲"
  },
  {
    "酒样名称": "白云边4#",
    "酒度": 45,
    "总分": 90.4,
    "设备": "砖窖",
    "发酵剂": "大曲"
  },
  {
    "酒样名称": "白云边5#",
    "酒度": 45,
    "总分": 88.4,
    "设备": "砖窖",
    "发酵剂": "大曲"
  },
  {
    "酒样名称": "口子窖1#",
    "酒度": 50,
    "总分": 94.0,
    "设备": "泥窖",
    "发酵剂": "大曲"
  },
  {
    "酒样名称": "口子窖2#",
    "酒度": 50,
    "总分": 93.0,
    "设备": "泥窖",
    "发酵剂": "大曲"
  },
  {
    "酒样名称": "口子窖3#",
    "酒度": 50,
    "总分": 91.8,
    "设备": "泥窖",
    "发酵剂": "大曲"
  },
  {
    "酒样名称": "口子窖4#",
    "酒度": 50,
    "总分": 90.0,
    "设备": "泥窖",
    "发酵剂": "大曲"
  },
  {
    "酒样名称": "口子窖5#",
    "酒度": 50,
    "总分": 88.4,
    "设备": "泥窖",
    "发酵剂": "大曲"
  },
  {
    "酒样名称": "西凤1#",
    "酒度": 55,
    "总分": 93.8,
    "设备": "泥窖",
    "发酵剂": "大曲"
  },
  {
    "酒样名称": "西凤2#",
    "酒度": 55,
    "总分": 93.0,
    "设备": "泥窖",
    "发酵剂": "大曲"
  },
  {
    "酒样名称": "西凤3#",
    "酒度": 55,
    "总分": 91.6,
    "设备": "泥窖",
    "发酵剂": "大曲"
  },
  {
    "酒样名称": "西凤4#",
    "酒度": 55,
    "总分": 90.0,
    "设备": "泥窖",
    "发酵剂": "大曲"
  },
  {
    "酒样名称": "西凤5#",
    "酒度": 55,
    "总分": 87.8,
    "设备": "泥窖",
    "发酵剂": "大曲"
  },
  {
    "酒样名称": "九江1#",
    "酒度": 32,
    "总分": 93.2,
    "设备": "发酵罐",
    "发酵剂": "小曲"
  },
  {
    "酒样名称": "九江2#",
    "酒度": 32,
    "总分": 92.0,
    "设备": "发酵罐",
    "发酵剂": "小曲"
  },
  {
    "酒样名称": "九江3#",
    "酒度": 32,
    "总分": 90.6,
    "设备": "发酵罐",
    "发酵剂": "小曲"
  },
  {
    "酒样名称": "九江4#",
    "酒度": 32,
    "总分": 89.0,
    "设备": "发酵罐",
    "发酵剂": "小曲"
  },
  {
    "酒样名称": "九江5#",
    "酒度": 32,
    "总分": 88.0,
    "设备": "发酵罐",
    "发酵剂": "小曲"
  },
  {
    "酒样名称": "四特1#",
    "酒度": 52,
    "总分": 93.8,
    "设备": "石窖",
    "发酵剂": "大曲"
  },
  {
    "酒样名称": "四特2#",
    "酒度": 52,
    "总分": 93.0,
    "设备": "石窖",
    "发酵剂": "大曲"
  },
  {
    "酒样名称": "四特3#",
    "酒度": 52,
    "总分": 91.6,
    "设备": "石窖",
    "发酵剂": "大曲"
  },
  {
    "酒样名称": "四特4#",
    "酒度": 52,
    "总分": 89.8,
    "设备": "石窖",
    "发酵剂": "大曲"
  },
  {
    "酒样名称": "四特5#",
    "酒度": 52,
    "总分": 88.0,
    "设备": "石窖",
    "发酵剂": "大曲"
  },
  {
    "酒样名称": "景芝1#",
    "酒度": 53,
    "总分": 94.0,
    "设备": "砖窖",
    "发酵剂": "大曲,麸曲"
  },
  {
    "酒样名称": "景芝2#",
    "酒度": 53,
    "总分": 93.4,
    "设备": "砖窖",
    "发酵剂": "大曲,麸曲"
  },
  {
    "酒样名称": "景芝3#",
    "酒度": 53,
    "总分": 91.2,
    "设备": "砖窖",
    "发酵剂": "大曲,麸曲"
  },
  {
    "酒样名称": "景芝4#",
    "酒度": 53,
    "总分": 90.4,
    "设备": "砖窖",
    "发酵剂": "大曲,麸曲"
  },
  {
    "酒样名称": "景芝5#",
    "酒度": 53,
    "总分": 89.4,
    "设备": "砖窖",
    "发酵剂": "大曲,麸曲"
  },
  {
    "酒样名称": "扳倒井1#",
    "酒度": 53,
    "总分": 93.8,
    "设备": "砖窖",
    "发酵剂": "大曲,麸曲"
  },
  {
    "酒样名称": "扳倒井2#",
    "酒度": 53,
    "总分": 93.0,
    "设备": "砖窖",
    "发酵剂": "大曲,麸曲"
  },
  {
    "酒样名称": "扳倒井3#",
    "酒度": 53,
    "总分": 92.0,
    "设备": "砖窖",
    "发酵剂": "大曲,麸曲"
  },
  {
    "酒样名称": "扳倒井4#",
    "酒度": 53,
    "总分": 90.2,
    "设备": "砖窖",
    "发酵剂": "大曲,麸曲"
  },
  {
    "酒样名称": "扳倒井5#",
    "酒度": 53,
    "总分": 88.4,
    "设备": "砖窖",
    "发酵剂": "大曲,麸曲"
  },
  {
    "酒样名称": "董酒1#",
    "酒度": 54,
    "总分": 94.0,
    "设备": "泥窖",
    "发酵剂": "大曲,小曲"
  },
  {
    "酒样名称": "董酒2#",
    "酒度": 54,
    "总分": 93.0,
    "设备": "泥窖",
    "发酵剂": "大曲,小曲"
  },
  {
    "酒样名称": "董酒3#",
    "酒度": 54,
    "总分": 92.0,
    "设备": "泥窖",
    "发酵剂": "大曲,小曲"
  },
  {
    "酒样名称": "董酒4#",
    "酒度": 54,
    "总分": 90.0,
    "设备": "泥窖",
    "发酵剂": "大曲,小曲"
  },
  {
    "酒样名称": "董酒5#",
    "酒度": 54,
    "总分": 88.2,
    "设备": "泥窖",
    "发酵剂": "大曲,小曲"
  },
  {
    "酒样名称": "老白干1#",
    "酒度": 54,
    "总分": 94.0,
    "设备": "地缸",
    "发酵剂": "大曲"
  },
  {
    "酒样名称": "老白干2#",
    "酒度": 54,
    "总分": 93.4,
    "设备": "地缸",
    "发酵剂": "大曲"
  },
  {
    "酒样名称": "老白干3#",
    "酒度": 54,
    "总分": 92.0,
    "设备": "地缸",
    "发酵剂": "大曲"
  },
  {
    "酒样名称": "老白干4#",
    "酒度": 54,
    "总分": 90.6,
    "设备": "地缸",
    "发酵剂": "大曲"
  },
  {
    "酒样名称": "老白干5#",
    "酒度": 54,
    "总分": 88.2,
    "设备": "地缸",
    "发酵剂": "大曲"
  },
  {
    "酒样名称": "酒鬼酒1#",
    "酒度": 54,
    "总分": 93.8,
    "设备": "泥窖",
    "发酵剂": "大曲,小曲"
  },
  {
    "酒样名称": "酒鬼酒2#",
    "酒度": 54,
    "总分": 92.8,
    "设备": "泥窖",
    "发酵剂": "大曲,小曲"
  },
  {
    "酒样名称": "酒鬼酒3#",
    "酒度": 54,
    "总分": 92.0,
    "设备": "泥窖",
    "发酵剂": "大曲,小曲"
  },
  {
    "酒样名称": "酒鬼酒4#",
    "酒度": 54,
    "总分": 90.0,
    "设备": "泥窖",
    "发酵剂": "大曲,小曲"
  },
  {
    "酒样名称": "酒鬼酒5#",
    "酒度": 54,
    "总分": 88.0,
    "设备": "泥窖",
    "发酵剂": "大曲,小曲"
  },
  {
    "酒样名称": "仰韶1#",
    "酒度": 53,
    "总分": 93.8,
    "设备": "陶缸,泥窖",
    "发酵剂": "大曲,小曲,麸曲"
  },
  {
    "酒样名称": "仰韶2#",
    "酒度": 53,
    "总分": 93.0,
    "设备": "陶缸,泥窖",
    "发酵剂": "大曲,小曲,麸曲"
  },
  {
    "酒样名称": "仰韶3#",
    "酒度": 53,
    "总分": 91.6,
    "设备": "陶缸,泥窖",
    "发酵剂": "大曲,小曲,麸曲"
  },
  {
    "酒样名称": "仰韶4#",
    "酒度": 53,
    "总分": 89.2,
    "设备": "陶缸,泥窖",
    "发酵剂": "大曲,小曲,麸曲"
  },
  {
    "酒样名称": "仰韶5#",
    "酒度": 53,
    "总分": 87.8,
    "设备": "陶缸,泥窖",
    "发酵剂": "大曲,小曲,麸曲"
  },
  {
    "酒样名称": "皇沟1#",
    "酒度": 53,
    "总分": 93.2,
    "设备": "石窖,泥窖",
    "发酵剂": "大曲,麸曲"
  },
  {
    "酒样名称": "皇沟2#",
    "酒度": 53,
    "总分": 92.4,
    "设备": "石窖,泥窖",
    "发酵剂": "大曲,麸曲"
  },
  {
    "酒样名称": "皇沟3#",
    "酒度": 53,
    "总分": 91.6,
    "设备": "石窖,泥窖",
    "发酵剂": "大曲,麸曲"
  },
  {
    "酒样名称": "皇沟4#",
    "酒度": 53,
    "总分": 89.2,
    "设备": "石窖,泥窖",
    "发酵剂": "大曲,麸曲"
  },
  {
    "酒样名称": "皇沟5#",
    "酒度": 53,
    "总分": 87.8,
    "设备": "石窖,泥窖",
    "发酵剂": "大曲,麸曲"
  },
  {
    "酒样名称": "牛栏山1#",
    "酒度": 53,
    "总分": 93.8,
    "设备": "地缸",
    "发酵剂": "大曲"
  },
  {
    "酒样名称": "牛栏山2#",
    "酒度": 53,
    "总分": 93.2,
    "设备": "地缸",
    "发酵剂": "大曲"
  },
  {
    "酒样名称": "牛栏山3#",
    "酒度": 53,
    "总分": 90.2,
    "设备": "地缸,瓷砖窖",
    "发酵剂": "大曲"
  },
  {
    "酒样名称": "牛栏山4#",
    "酒度": 53,
    "总分": 89.6,
    "设备": "地缸",
    "发酵剂": "大曲"
  },
  {
    "酒样名称": "牛栏山5#",
    "酒度": 53,
    "总分": 88.2,
    "设备": "地缸",
    "发酵剂": "大曲"
  },
    {
    "酒样名称": "红星1#",
    "酒度": 52,
    "总分": 93.4,
    "设备": "地缸",
    "发酵剂": "大曲"
  },
  {
    "酒样名称": "红星2#",
    "酒度": 52,
    "总分": 92.4,
    "设备": "地缸",
    "发酵剂": "大曲"
  },
  {
    "酒样名称": "红星3#",
    "酒度": 52,
    "总分": 91.2,
    "设备": "水泥池",
    "发酵剂": "大曲"
  },
  {
    "酒样名称": "红星4#",
    "酒度": 52,
    "总分": 89.4,
    "设备": "水泥池",
    "发酵剂": "大曲"
  },
  {
    "酒样名称": "红星5#",
    "酒度": 52,
    "总分": 87.6,
    "设备": "水泥池",
    "发酵剂": "大曲,麸曲,酵母"
  }
]